y2/__init__.py
y2/_base_client.py
y2/_client.py
y2/_compat.py
y2/_constants.py
y2/_exceptions.py
y2/_files.py
y2/_models.py
y2/_qs.py
y2/_resource.py
y2/_response.py
y2/_streaming.py
y2/_types.py
y2/_version.py
y2/py.typed
y2/_utils/__init__.py
y2/_utils/_compat.py
y2/_utils/_datetime_parse.py
y2/_utils/_logs.py
y2/_utils/_proxy.py
y2/_utils/_reflection.py
y2/_utils/_resources_proxy.py
y2/_utils/_streams.py
y2/_utils/_sync.py
y2/_utils/_transform.py
y2/_utils/_typing.py
y2/_utils/_utils.py
y2/lib/.keep
y2/resources/__init__.py
y2/resources/news.py
y2/resources/profiles.py
y2/resources/reports.py
y2/types/__init__.py
y2/types/audio_metadata.py
y2/types/news_get_recaps_params.py
y2/types/news_get_recaps_response.py
y2/types/news_list_feeds_response.py
y2/types/news_list_params.py
y2/types/news_list_response.py
y2/types/profile_list_response.py
y2/types/report_list_params.py
y2/types/report_list_response.py
y2/types/report_retrieve_audio_params.py
y2/types/report_retrieve_audio_response.py
y2/types/report_retrieve_response.py
y2/types/timeframe_enum.py
y2/types/topic_enum.py
y2_py-0.2.0.dist-info/METADATA
y2_py-0.2.0.dist-info/WHEEL
y2_py-0.2.0.dist-info/licenses/LICENSE
y2_py-0.2.0.dist-info/RECORD
